nmfViewer/NMFView.py
nmfViewer/NMFWindow.py
nmfViewer/__init__.py
nmfViewer/controls/ControlsWidget.py
nmfViewer/controls/EvaluationWidget.py
nmfViewer/controls/MetricsWidget.py
nmfViewer/controls/NMFTreeView.py
nmfViewer/controls/Tabs.py
nmfViewer/controls/ViewControls.py
nmfViewer/controls/__init__.py
nmfViewer/nmf_view/FeatureMatrixView.py
nmfViewer/nmf_view/MatrixHighlightView.py
nmfViewer/nmf_view/MatrixView.py
nmfViewer/nmf_view/ThresholdBox.py
nmfViewer/nmf_view/__init__.py
nmfViewer/nmf_view/threshold_slider/DoubleSlider.py
nmfViewer/nmf_view/threshold_slider/ThresholdSlider.py
nmfViewer/nmf_view/threshold_slider/__init__.py
nmfViewer/utils/DataUtils.py
nmfViewer/utils/FileUtils.py
nmfViewer/utils/__init__.py
nmfviewer-1.0.0.dist-info/licenses/LICENSE
nmfviewer-1.0.0.dist-info/METADATA
nmfviewer-1.0.0.dist-info/WHEEL
nmfviewer-1.0.0.dist-info/top_level.txt
nmfviewer-1.0.0.dist-info/RECORD
