Metadata-Version: 2.4
Name: nmfViewer
Version: 1.0.0
Summary: Python Application which enables users to quickly visualize NMF decomposition.
Requires-Python: >=3.11
License-File: LICENSE
Requires-Dist: automatic-spike-detection
Requires-Dist: pyqtgraph
Requires-Dist: PyQt6
Requires-Dist: pandas
Requires-Dist: numpy
Requires-Dist: typing-extensions
Dynamic: license-file
